s3_tool/__init__.py
s3_tool/cant_use_s3t.py
s3_tool/fix_bug_s3t.py
s3_tool/s3_related.py
s3_tool/sandbox1_s3t.py
s3_toolkit-0.1.0.dist-info/METADATA
s3_toolkit-0.1.0.dist-info/WHEEL
s3_toolkit-0.1.0.dist-info/top_level.txt
s3_toolkit-0.1.0.dist-info/RECORD
