Metadata-Version: 2.1
Name: s3-toolkit
Version: 0.1.0
Summary: package to help you manage file in AWS s3 storage
Author: Dear Norathee
License: MIT
